{
  "title": "Inbox/Outbox Metrics Dashboard",
  "uid": "inbox-outbox-metrics",
  "timezone": "browser",
  "editable": true,
  "schemaVersion": 39,
  "version": 1,
  "refresh": "10s",
  "time": { "from": "now-15m", "to": "now" },
  "templating": {
    "list": [
      {
        "name": "service",
        "type": "query",
        "label": "Service",
        "hide": 0,
        "includeAll": true,
        "multi": true,
        "query": "label_values(outbox_events_total, service)",
        "refresh": 1,
        "current": { "text": "All", "value": "$__all" }
      },
      {
        "name": "interval",
        "type": "interval",
        "label": "Group by",
        "hide": 0,
        "current": { "text": "1m", "value": "1m" },
        "options": [
          { "text": "10s", "value": "10s", "selected": false },
          { "text": "30s", "value": "30s", "selected": false },
          { "text": "1m", "value": "1m", "selected": true },
          { "text": "5m", "value": "5m", "selected": false },
          { "text": "15m", "value": "15m", "selected": false },
          { "text": "1h", "value": "1h", "selected": false }
        ],
        "query": "10s,30s,1m,5m,15m,1h"
      }
    ]
  },
  "annotations": {
    "list": []
  },
  "panels": [
    {
      "type": "row",
      "title": "Overview",
      "gridPos": { "h": 1, "w": 24, "x": 0, "y": 0 },
      "collapsed": false
    },
    {
      "type": "stat",
      "title": "Outbox Publish Rate",
      "gridPos": { "h": 4, "w": 4, "x": 0, "y": 1 },
      "fieldConfig": {
        "defaults": {
          "color": { "mode": "thresholds" },
          "thresholds": {
            "mode": "absolute",
            "steps": [
              { "color": "green", "value": null },
              { "color": "yellow", "value": 50 },
              { "color": "red", "value": 100 }
            ]
          },
          "unit": "reqps"
        }
      },
      "options": {
        "colorMode": "value",
        "graphMode": "area",
        "justifyMode": "auto",
        "textMode": "auto",
        "reduceOptions": { "calcs": ["lastNotNull"], "fields": "", "values": false }
      },
      "targets": [
        {
          "expr": "sum(rate(outbox_events_total{service=~\"$service\", status=\"published\"}[$interval]))",
          "legendFormat": "Published"
        }
      ]
    },
    {
      "type": "stat",
      "title": "Outbox Queue Size",
      "gridPos": { "h": 4, "w": 4, "x": 4, "y": 1 },
      "fieldConfig": {
        "defaults": {
          "color": { "mode": "thresholds" },
          "thresholds": {
            "mode": "absolute",
            "steps": [
              { "color": "green", "value": null },
              { "color": "yellow", "value": 10 },
              { "color": "red", "value": 50 }
            ]
          },
          "unit": "short"
        }
      },
      "options": {
        "colorMode": "value",
        "graphMode": "area",
        "justifyMode": "auto",
        "textMode": "auto",
        "reduceOptions": { "calcs": ["lastNotNull"], "fields": "", "values": false }
      },
      "targets": [
        {
          "expr": "sum(outbox_queue_size{service=~\"$service\"})",
          "legendFormat": "Queue"
        }
      ]
    },
    {
      "type": "stat",
      "title": "Outbox Error Rate",
      "gridPos": { "h": 4, "w": 4, "x": 8, "y": 1 },
      "fieldConfig": {
        "defaults": {
          "color": { "mode": "thresholds" },
          "thresholds": {
            "mode": "absolute",
            "steps": [
              { "color": "green", "value": null },
              { "color": "yellow", "value": 1 },
              { "color": "red", "value": 5 }
            ]
          },
          "unit": "percentunit"
        }
      },
      "options": {
        "colorMode": "value",
        "graphMode": "area",
        "justifyMode": "auto",
        "textMode": "auto",
        "reduceOptions": { "calcs": ["lastNotNull"], "fields": "", "values": false }
      },
      "targets": [
        {
          "expr": "sum(rate(outbox_events_total{service=~\"$service\", status=\"failed\"}[$interval])) / sum(rate(outbox_events_total{service=~\"$service\"}[$interval]))",
          "legendFormat": "Error Rate"
        }
      ]
    },
    {
      "type": "stat",
      "title": "Inbox Receive Rate",
      "gridPos": { "h": 4, "w": 4, "x": 12, "y": 1 },
      "fieldConfig": {
        "defaults": {
          "color": { "mode": "thresholds" },
          "thresholds": {
            "mode": "absolute",
            "steps": [
              { "color": "green", "value": null },
              { "color": "yellow", "value": 50 },
              { "color": "red", "value": 100 }
            ]
          },
          "unit": "reqps"
        }
      },
      "options": {
        "colorMode": "value",
        "graphMode": "area",
        "justifyMode": "auto",
        "textMode": "auto",
        "reduceOptions": { "calcs": ["lastNotNull"], "fields": "", "values": false }
      },
      "targets": [
        {
          "expr": "sum(rate(inbox_events_total{service=~\"$service\", status=\"received\"}[$interval]))",
          "legendFormat": "Received"
        }
      ]
    },
    {
      "type": "stat",
      "title": "Inbox Queue Size",
      "gridPos": { "h": 4, "w": 4, "x": 16, "y": 1 },
      "fieldConfig": {
        "defaults": {
          "color": { "mode": "thresholds" },
          "thresholds": {
            "mode": "absolute",
            "steps": [
              { "color": "green", "value": null },
              { "color": "yellow", "value": 10 },
              { "color": "red", "value": 50 }
            ]
          },
          "unit": "short"
        }
      },
      "options": {
        "colorMode": "value",
        "graphMode": "area",
        "justifyMode": "auto",
        "textMode": "auto",
        "reduceOptions": { "calcs": ["lastNotNull"], "fields": "", "values": false }
      },
      "targets": [
        {
          "expr": "sum(inbox_queue_size{service=~\"$service\"})",
          "legendFormat": "Queue"
        }
      ]
    },
    {
      "type": "stat",
      "title": "Inbox Error Rate",
      "gridPos": { "h": 4, "w": 4, "x": 20, "y": 1 },
      "fieldConfig": {
        "defaults": {
          "color": { "mode": "thresholds" },
          "thresholds": {
            "mode": "absolute",
            "steps": [
              { "color": "green", "value": null },
              { "color": "yellow", "value": 1 },
              { "color": "red", "value": 5 }
            ]
          },
          "unit": "percentunit"
        }
      },
      "options": {
        "colorMode": "value",
        "graphMode": "area",
        "justifyMode": "auto",
        "textMode": "auto",
        "reduceOptions": { "calcs": ["lastNotNull"], "fields": "", "values": false }
      },
      "targets": [
        {
          "expr": "sum(rate(inbox_events_total{service=~\"$service\", status=\"failed\"}[$interval])) / sum(rate(inbox_events_total{service=~\"$service\"}[$interval]))",
          "legendFormat": "Error Rate"
        }
      ]
    },
    {
      "type": "row",
      "title": "Outbox",
      "gridPos": { "h": 1, "w": 24, "x": 0, "y": 5 },
      "collapsed": false
    },
    {
      "type": "timeseries",
      "title": "Outbox Events by Topic",
      "gridPos": { "h": 8, "w": 12, "x": 0, "y": 6 },
      "fieldConfig": {
        "defaults": {
          "custom": {
            "drawStyle": "line",
            "lineWidth": 1,
            "fillOpacity": 20,
            "gradientMode": "opacity",
            "spanNulls": false,
            "showPoints": "never",
            "stacking": { "mode": "none" }
          },
          "unit": "reqps"
        }
      },
      "options": {
        "legend": { "displayMode": "table", "placement": "right", "calcs": ["mean", "max"] },
        "tooltip": { "mode": "multi", "sort": "desc" }
      },
      "targets": [
        {
          "expr": "sum by (topic, event_name) (rate(outbox_events_total{service=~\"$service\", status=\"published\"}[$interval]))",
          "legendFormat": "{{topic}} / {{event_name}}"
        }
      ]
    },
    {
      "type": "timeseries",
      "title": "Outbox Publish Latency (p95)",
      "gridPos": { "h": 8, "w": 12, "x": 12, "y": 6 },
      "fieldConfig": {
        "defaults": {
          "custom": {
            "drawStyle": "line",
            "lineWidth": 1,
            "fillOpacity": 20,
            "gradientMode": "opacity",
            "spanNulls": false,
            "showPoints": "never"
          },
          "unit": "s"
        }
      },
      "options": {
        "legend": { "displayMode": "table", "placement": "right", "calcs": ["mean", "max"] },
        "tooltip": { "mode": "multi", "sort": "desc" }
      },
      "targets": [
        {
          "expr": "histogram_quantile(0.95, sum by (topic, le) (rate(outbox_event_duration_seconds_bucket{service=~\"$service\", status=\"published\"}[$interval])))",
          "legendFormat": "{{topic}}"
        }
      ]
    },
    {
      "type": "timeseries",
      "title": "Outbox Queue Size Over Time",
      "gridPos": { "h": 6, "w": 8, "x": 0, "y": 14 },
      "fieldConfig": {
        "defaults": {
          "custom": {
            "drawStyle": "line",
            "lineWidth": 2,
            "fillOpacity": 30,
            "gradientMode": "opacity",
            "spanNulls": false,
            "showPoints": "never"
          },
          "unit": "short",
          "color": { "mode": "palette-classic" }
        }
      },
      "options": {
        "legend": { "displayMode": "list", "placement": "bottom" },
        "tooltip": { "mode": "multi" }
      },
      "targets": [
        {
          "expr": "sum by (service) (outbox_queue_size{service=~\"$service\"})",
          "legendFormat": "{{service}}"
        }
      ]
    },
    {
      "type": "timeseries",
      "title": "Outbox Failed Events",
      "gridPos": { "h": 6, "w": 8, "x": 8, "y": 14 },
      "fieldConfig": {
        "defaults": {
          "custom": {
            "drawStyle": "bars",
            "lineWidth": 1,
            "fillOpacity": 80,
            "gradientMode": "none",
            "spanNulls": false,
            "showPoints": "never"
          },
          "unit": "short",
          "color": { "fixedColor": "red", "mode": "fixed" }
        }
      },
      "options": {
        "legend": { "displayMode": "list", "placement": "bottom" },
        "tooltip": { "mode": "multi" }
      },
      "targets": [
        {
          "expr": "sum by (topic, event_name) (increase(outbox_events_total{service=~\"$service\", status=\"failed\"}[$interval]))",
          "legendFormat": "{{topic}} / {{event_name}}"
        }
      ]
    },
    {
      "type": "timeseries",
      "title": "Outbox Retries",
      "gridPos": { "h": 6, "w": 8, "x": 16, "y": 14 },
      "fieldConfig": {
        "defaults": {
          "custom": {
            "drawStyle": "bars",
            "lineWidth": 1,
            "fillOpacity": 80,
            "gradientMode": "none",
            "spanNulls": false,
            "showPoints": "never"
          },
          "unit": "short",
          "color": { "fixedColor": "orange", "mode": "fixed" }
        }
      },
      "options": {
        "legend": { "displayMode": "list", "placement": "bottom" },
        "tooltip": { "mode": "multi" }
      },
      "targets": [
        {
          "expr": "sum by (topic, event_name) (increase(outbox_events_total{service=~\"$service\", status=\"retry\"}[$interval]))",
          "legendFormat": "{{topic}} / {{event_name}}"
        }
      ]
    },
    {
      "type": "row",
      "title": "Inbox",
      "gridPos": { "h": 1, "w": 24, "x": 0, "y": 20 },
      "collapsed": false
    },
    {
      "type": "timeseries",
      "title": "Inbox Events by Topic",
      "gridPos": { "h": 8, "w": 12, "x": 0, "y": 21 },
      "fieldConfig": {
        "defaults": {
          "custom": {
            "drawStyle": "line",
            "lineWidth": 1,
            "fillOpacity": 20,
            "gradientMode": "opacity",
            "spanNulls": false,
            "showPoints": "never",
            "stacking": { "mode": "none" }
          },
          "unit": "reqps"
        }
      },
      "options": {
        "legend": { "displayMode": "table", "placement": "right", "calcs": ["mean", "max"] },
        "tooltip": { "mode": "multi", "sort": "desc" }
      },
      "targets": [
        {
          "expr": "sum by (topic, event_name) (rate(inbox_events_total{service=~\"$service\", status=\"processed\"}[$interval]))",
          "legendFormat": "{{topic}} / {{event_name}}"
        }
      ]
    },
    {
      "type": "timeseries",
      "title": "Inbox Processing Latency (p95)",
      "gridPos": { "h": 8, "w": 12, "x": 12, "y": 21 },
      "fieldConfig": {
        "defaults": {
          "custom": {
            "drawStyle": "line",
            "lineWidth": 1,
            "fillOpacity": 20,
            "gradientMode": "opacity",
            "spanNulls": false,
            "showPoints": "never"
          },
          "unit": "s"
        }
      },
      "options": {
        "legend": { "displayMode": "table", "placement": "right", "calcs": ["mean", "max"] },
        "tooltip": { "mode": "multi", "sort": "desc" }
      },
      "targets": [
        {
          "expr": "histogram_quantile(0.95, sum by (topic, le) (rate(inbox_event_duration_seconds_bucket{service=~\"$service\", status=\"processed\"}[$interval])))",
          "legendFormat": "{{topic}}"
        }
      ]
    },
    {
      "type": "timeseries",
      "title": "Inbox Queue Size Over Time",
      "gridPos": { "h": 6, "w": 8, "x": 0, "y": 29 },
      "fieldConfig": {
        "defaults": {
          "custom": {
            "drawStyle": "line",
            "lineWidth": 2,
            "fillOpacity": 30,
            "gradientMode": "opacity",
            "spanNulls": false,
            "showPoints": "never"
          },
          "unit": "short",
          "color": { "mode": "palette-classic" }
        }
      },
      "options": {
        "legend": { "displayMode": "list", "placement": "bottom" },
        "tooltip": { "mode": "multi" }
      },
      "targets": [
        {
          "expr": "sum by (service) (inbox_queue_size{service=~\"$service\"})",
          "legendFormat": "{{service}}"
        }
      ]
    },
    {
      "type": "timeseries",
      "title": "Inbox Failed Events",
      "gridPos": { "h": 6, "w": 8, "x": 8, "y": 29 },
      "fieldConfig": {
        "defaults": {
          "custom": {
            "drawStyle": "bars",
            "lineWidth": 1,
            "fillOpacity": 80,
            "gradientMode": "none",
            "spanNulls": false,
            "showPoints": "never"
          },
          "unit": "short",
          "color": { "fixedColor": "red", "mode": "fixed" }
        }
      },
      "options": {
        "legend": { "displayMode": "list", "placement": "bottom" },
        "tooltip": { "mode": "multi" }
      },
      "targets": [
        {
          "expr": "sum by (topic, event_name) (increase(inbox_events_total{service=~\"$service\", status=\"failed\"}[$interval]))",
          "legendFormat": "{{topic}} / {{event_name}}"
        }
      ]
    },
    {
      "type": "timeseries",
      "title": "Inbox Duplicates",
      "gridPos": { "h": 6, "w": 8, "x": 16, "y": 29 },
      "fieldConfig": {
        "defaults": {
          "custom": {
            "drawStyle": "bars",
            "lineWidth": 1,
            "fillOpacity": 80,
            "gradientMode": "none",
            "spanNulls": false,
            "showPoints": "never"
          },
          "unit": "short",
          "color": { "fixedColor": "yellow", "mode": "fixed" }
        }
      },
      "options": {
        "legend": { "displayMode": "list", "placement": "bottom" },
        "tooltip": { "mode": "multi" }
      },
      "targets": [
        {
          "expr": "sum by (topic, event_name) (increase(inbox_events_total{service=~\"$service\", status=\"duplicate\"}[$interval]))",
          "legendFormat": "{{topic}} / {{event_name}}"
        }
      ]
    },
    {
      "type": "row",
      "title": "Detailed Tables",
      "gridPos": { "h": 1, "w": 24, "x": 0, "y": 35 },
      "collapsed": false
    },
    {
      "type": "table",
      "title": "Top Outbox Events (Last 5m)",
      "gridPos": { "h": 8, "w": 12, "x": 0, "y": 36 },
      "fieldConfig": {
        "defaults": {
          "custom": { "align": "auto", "filterable": true }
        },
        "overrides": [
          {
            "matcher": { "id": "byName", "options": "Topic" },
            "properties": [{ "id": "custom.width", "value": 150 }]
          },
          {
            "matcher": { "id": "byName", "options": "Event" },
            "properties": [{ "id": "custom.width", "value": 200 }]
          },
          {
            "matcher": { "id": "byName", "options": "Published" },
            "properties": [
              { "id": "unit", "value": "short" },
              { "id": "decimals", "value": 0 }
            ]
          },
          {
            "matcher": { "id": "byName", "options": "Failed" },
            "properties": [
              { "id": "unit", "value": "short" },
              { "id": "decimals", "value": 0 },
              { "id": "custom.cellOptions", "value": { "type": "color-background", "mode": "gradient" } },
              { "id": "color", "value": { "mode": "thresholds" } },
              { "id": "thresholds", "value": { "mode": "absolute", "steps": [{ "color": "transparent", "value": null }, { "color": "red", "value": 1 }] } }
            ]
          },
          {
            "matcher": { "id": "byName", "options": "Retries" },
            "properties": [
              { "id": "unit", "value": "short" },
              { "id": "decimals", "value": 0 },
              { "id": "custom.cellOptions", "value": { "type": "color-background", "mode": "gradient" } },
              { "id": "color", "value": { "mode": "thresholds" } },
              { "id": "thresholds", "value": { "mode": "absolute", "steps": [{ "color": "transparent", "value": null }, { "color": "orange", "value": 1 }] } }
            ]
          },
          {
            "matcher": { "id": "byName", "options": "Avg Duration" },
            "properties": [
              { "id": "unit", "value": "s" },
              { "id": "decimals", "value": 3 }
            ]
          }
        ]
      },
      "options": {
        "showHeader": true,
        "sortBy": [{ "displayName": "Published", "desc": true }]
      },
      "transformations": [
        {
          "id": "joinByField",
          "options": { "byField": "event_name", "mode": "outer" }
        },
        {
          "id": "organize",
          "options": {
            "renameByName": {
              "topic": "Topic",
              "event_name": "Event",
              "Value #A": "Published",
              "Value #B": "Failed",
              "Value #C": "Retries",
              "Value #D": "Avg Duration"
            }
          }
        }
      ],
      "targets": [
        {
          "expr": "round(sum by (topic, event_name) (increase(outbox_events_total{service=~\"$service\", status=\"published\"}[5m])))",
          "legendFormat": "{{event_name}}",
          "format": "table",
          "instant": true,
          "refId": "A"
        },
        {
          "expr": "round(sum by (topic, event_name) (increase(outbox_events_total{service=~\"$service\", status=\"failed\"}[5m])))",
          "legendFormat": "{{event_name}}",
          "format": "table",
          "instant": true,
          "refId": "B"
        },
        {
          "expr": "round(sum by (topic, event_name) (increase(outbox_events_total{service=~\"$service\", status=\"retry\"}[5m])))",
          "legendFormat": "{{event_name}}",
          "format": "table",
          "instant": true,
          "refId": "C"
        },
        {
          "expr": "sum by (topic, event_name) (rate(outbox_event_duration_seconds_sum{service=~\"$service\", status=\"published\"}[5m])) / sum by (topic, event_name) (rate(outbox_event_duration_seconds_count{service=~\"$service\", status=\"published\"}[5m]))",
          "legendFormat": "{{event_name}}",
          "format": "table",
          "instant": true,
          "refId": "D"
        }
      ]
    },
    {
      "type": "table",
      "title": "Top Inbox Events (Last 5m)",
      "gridPos": { "h": 8, "w": 12, "x": 12, "y": 36 },
      "fieldConfig": {
        "defaults": {
          "custom": { "align": "auto", "filterable": true }
        },
        "overrides": [
          {
            "matcher": { "id": "byName", "options": "Topic" },
            "properties": [{ "id": "custom.width", "value": 150 }]
          },
          {
            "matcher": { "id": "byName", "options": "Event" },
            "properties": [{ "id": "custom.width", "value": 200 }]
          },
          {
            "matcher": { "id": "byName", "options": "Received" },
            "properties": [
              { "id": "unit", "value": "short" },
              { "id": "decimals", "value": 0 }
            ]
          },
          {
            "matcher": { "id": "byName", "options": "Processed" },
            "properties": [
              { "id": "unit", "value": "short" },
              { "id": "decimals", "value": 0 }
            ]
          },
          {
            "matcher": { "id": "byName", "options": "Failed" },
            "properties": [
              { "id": "unit", "value": "short" },
              { "id": "decimals", "value": 0 },
              { "id": "custom.cellOptions", "value": { "type": "color-background", "mode": "gradient" } },
              { "id": "color", "value": { "mode": "thresholds" } },
              { "id": "thresholds", "value": { "mode": "absolute", "steps": [{ "color": "transparent", "value": null }, { "color": "red", "value": 1 }] } }
            ]
          },
          {
            "matcher": { "id": "byName", "options": "Duplicates" },
            "properties": [
              { "id": "unit", "value": "short" },
              { "id": "decimals", "value": 0 },
              { "id": "custom.cellOptions", "value": { "type": "color-background", "mode": "gradient" } },
              { "id": "color", "value": { "mode": "thresholds" } },
              { "id": "thresholds", "value": { "mode": "absolute", "steps": [{ "color": "transparent", "value": null }, { "color": "yellow", "value": 1 }] } }
            ]
          },
          {
            "matcher": { "id": "byName", "options": "Avg Duration" },
            "properties": [
              { "id": "unit", "value": "s" },
              { "id": "decimals", "value": 3 }
            ]
          }
        ]
      },
      "options": {
        "showHeader": true,
        "sortBy": [{ "displayName": "Processed", "desc": true }]
      },
      "transformations": [
        {
          "id": "joinByField",
          "options": { "byField": "event_name", "mode": "outer" }
        },
        {
          "id": "organize",
          "options": {
            "renameByName": {
              "topic": "Topic",
              "event_name": "Event",
              "Value #A": "Received",
              "Value #B": "Processed",
              "Value #C": "Failed",
              "Value #D": "Duplicates",
              "Value #E": "Avg Duration"
            }
          }
        }
      ],
      "targets": [
        {
          "expr": "round(sum by (topic, event_name) (increase(inbox_events_total{service=~\"$service\", status=\"received\"}[5m])))",
          "legendFormat": "{{event_name}}",
          "format": "table",
          "instant": true,
          "refId": "A"
        },
        {
          "expr": "round(sum by (topic, event_name) (increase(inbox_events_total{service=~\"$service\", status=\"processed\"}[5m])))",
          "legendFormat": "{{event_name}}",
          "format": "table",
          "instant": true,
          "refId": "B"
        },
        {
          "expr": "round(sum by (topic, event_name) (increase(inbox_events_total{service=~\"$service\", status=\"failed\"}[5m])))",
          "legendFormat": "{{event_name}}",
          "format": "table",
          "instant": true,
          "refId": "C"
        },
        {
          "expr": "round(sum by (topic, event_name) (increase(inbox_events_total{service=~\"$service\", status=\"duplicate\"}[5m])))",
          "legendFormat": "{{event_name}}",
          "format": "table",
          "instant": true,
          "refId": "D"
        },
        {
          "expr": "sum by (topic, event_name) (rate(inbox_event_duration_seconds_sum{service=~\"$service\", status=\"processed\"}[5m])) / sum by (topic, event_name) (rate(inbox_event_duration_seconds_count{service=~\"$service\", status=\"processed\"}[5m]))",
          "legendFormat": "{{event_name}}",
          "format": "table",
          "instant": true,
          "refId": "E"
        }
      ]
    },
    {
      "type": "row",
      "title": "Latency Distribution",
      "gridPos": { "h": 1, "w": 24, "x": 0, "y": 44 },
      "collapsed": false
    },
    {
      "type": "timeseries",
      "title": "Outbox Publish Latency Percentiles",
      "gridPos": { "h": 8, "w": 12, "x": 0, "y": 45 },
      "fieldConfig": {
        "defaults": {
          "custom": {
            "drawStyle": "line",
            "lineWidth": 1,
            "fillOpacity": 10,
            "gradientMode": "opacity",
            "spanNulls": false,
            "showPoints": "never"
          },
          "unit": "s"
        }
      },
      "options": {
        "legend": { "displayMode": "list", "placement": "bottom" },
        "tooltip": { "mode": "multi", "sort": "desc" }
      },
      "targets": [
        {
          "expr": "histogram_quantile(0.50, sum(rate(outbox_event_duration_seconds_bucket{service=~\"$service\", status=\"published\"}[$interval])) by (le))",
          "legendFormat": "p50"
        },
        {
          "expr": "histogram_quantile(0.90, sum(rate(outbox_event_duration_seconds_bucket{service=~\"$service\", status=\"published\"}[$interval])) by (le))",
          "legendFormat": "p90"
        },
        {
          "expr": "histogram_quantile(0.95, sum(rate(outbox_event_duration_seconds_bucket{service=~\"$service\", status=\"published\"}[$interval])) by (le))",
          "legendFormat": "p95"
        },
        {
          "expr": "histogram_quantile(0.99, sum(rate(outbox_event_duration_seconds_bucket{service=~\"$service\", status=\"published\"}[$interval])) by (le))",
          "legendFormat": "p99"
        }
      ]
    },
    {
      "type": "timeseries",
      "title": "Inbox Processing Latency Percentiles",
      "gridPos": { "h": 8, "w": 12, "x": 12, "y": 45 },
      "fieldConfig": {
        "defaults": {
          "custom": {
            "drawStyle": "line",
            "lineWidth": 1,
            "fillOpacity": 10,
            "gradientMode": "opacity",
            "spanNulls": false,
            "showPoints": "never"
          },
          "unit": "s"
        }
      },
      "options": {
        "legend": { "displayMode": "list", "placement": "bottom" },
        "tooltip": { "mode": "multi", "sort": "desc" }
      },
      "targets": [
        {
          "expr": "histogram_quantile(0.50, sum(rate(inbox_event_duration_seconds_bucket{service=~\"$service\", status=\"processed\"}[$interval])) by (le))",
          "legendFormat": "p50"
        },
        {
          "expr": "histogram_quantile(0.90, sum(rate(inbox_event_duration_seconds_bucket{service=~\"$service\", status=\"processed\"}[$interval])) by (le))",
          "legendFormat": "p90"
        },
        {
          "expr": "histogram_quantile(0.95, sum(rate(inbox_event_duration_seconds_bucket{service=~\"$service\", status=\"processed\"}[$interval])) by (le))",
          "legendFormat": "p95"
        },
        {
          "expr": "histogram_quantile(0.99, sum(rate(inbox_event_duration_seconds_bucket{service=~\"$service\", status=\"processed\"}[$interval])) by (le))",
          "legendFormat": "p99"
        }
      ]
    }
  ]
}
